[
  {
    "question": "Tidak hanya menorehkan banyak prestasi bagi para atlet Indonesia yang bertanding. Secara keseluruhan, Indonesia dapat dikatakan meninggalkan kesan baik bagi gelaran SEA Games 2023 Kamboja. Pasalnya, dalam video yang beredar di media sosial beredar terlihat salah satu tim medis Indonesia membersihkan sampah di pinggir venue Boat Race, Prek Kampot, Kampot City. Hal terpuji yang dilakukan Indonesia di SEA Games 2023 juga tidak berhenti sampai di situ, dalam euforia kemenangan final sepak bola SEA Games 2023, suporter Indonesia juga melakukan aksi bersih-bersih di Olympic Stadium, Phnom Penh, Kamboja. Sikap yang ditunjukkan supporter Indonesia tersebut sesuai dengan nilai Pancasila, yang juga merupakan fungsi Pancasila sebagai …",
    "options": [
      {"A.": "Dasar Negara"},
      {"B.": "Kepribadian Bangsa"},
      {"C.": "Pedoman Bangsa"},
      {"D.": "Jiwa Bangsa"},
      {"E.": "Falsafah Hidup Bangsa"}
    ],
    "correct_answer": {"B": "Kepribadian Bangsa"},
    "discussion": {
      "text": "Fungsi Pancasila sebagai Kepribadian bangsa qrtinya suatu sikap mental dan tingkah laku yang mempunyai ciri khas tersendiri sehingga mampu dibedakan dengan bangsa lainnya di seluruh dunia. Dalam narasi tersebut diperlihatkan sikap hormat bangsa Indonesia yang datang sebagai tamu dengan membersihkan tempat pertandingan sesuai pertandingan selesai.",
      "url": "https://bpip.go.id/assets/images/berita/2021/08/09/8951004.jpg"
    }
  }
]
